locate_pixelcolor_cpp/README.MD
locate_pixelcolor_cpp/__init__.py
locate_pixelcolor_cpp/requirements.txt
locate_pixelcolor_cpp/thirdparty.json
locate_pixelcolor_cpp-0.10.dist-info/LICENSE.rst
locate_pixelcolor_cpp-0.10.dist-info/METADATA
locate_pixelcolor_cpp-0.10.dist-info/WHEEL
locate_pixelcolor_cpp-0.10.dist-info/top_level.txt
locate_pixelcolor_cpp-0.10.dist-info/RECORD
