Metadata-Version: 2.1
Name: locate-pixelcolor-cpp
Version: 0.10
Summary: Locate RGB values in a picture! Up to 10x faster than NumPy, 100x faster than PIL.
Home-page: https://github.com/hansalemaos/locate_pixelcolor_cpp
Author: Johannes Fischer
Author-email: <aulasparticularesdealemaosp@gmail.com>
License: MIT
Keywords: rgb,locate,color,colors,numpy,c++
Classifier: Development Status :: 4 - Beta
Classifier: Programming Language :: Python :: 3 :: Only
Classifier: Programming Language :: Python :: 3.9
Classifier: Topic :: Scientific/Engineering :: Visualization
Classifier: Topic :: Software Development :: Libraries :: Python Modules
Classifier: Topic :: Text Editors :: Text Processing
Classifier: Topic :: Text Processing :: General
Classifier: Topic :: Text Processing :: Indexing
Classifier: Topic :: Text Processing :: Filters
Classifier: Topic :: Utilities
License-File: LICENSE.rst
Requires-Dist: flexible-partial
Requires-Dist: numpy
Requires-Dist: opencv-python
Requires-Dist: touchtouch
